<?xml version="1.0" encoding="utf-8" ?>
<dwsync>
<file name="animated.less" server="9fcd069a.7host.cn:90" local="131237379366574325" remote="131185980000000000" Dst="0" />
<file name="bordered-pulled.less" server="9fcd069a.7host.cn:90" local="131237379368449345" remote="131185980000000000" Dst="0" />
<file name="core.less" server="9fcd069a.7host.cn:90" local="131237379368918108" remote="131185980000000000" Dst="0" />
<file name="fixed-width.less" server="9fcd069a.7host.cn:90" local="131237379369230615" remote="131185980000000000" Dst="0" />
<file name="font-awesome.less" server="9fcd069a.7host.cn:90" local="131237379371105641" remote="131185980000000000" Dst="0" />
<file name="larger.less" server="9fcd069a.7host.cn:90" local="131237379371574396" remote="131185980000000000" Dst="0" />
<file name="icons.less" server="9fcd069a.7host.cn:90" local="131237379372355755" remote="131185980000000000" Dst="0" />
<file name="list.less" server="9fcd069a.7host.cn:90" local="131237379373761917" remote="131185980000000000" Dst="0" />
<file name="mixins.less" server="9fcd069a.7host.cn:90" local="131237379374074422" remote="131185980000000000" Dst="0" />
<file name="path.less" server="9fcd069a.7host.cn:90" local="131237379374855695" remote="131185980000000000" Dst="0" />
<file name="rotated-flipped.less" server="9fcd069a.7host.cn:90" local="131237379376105704" remote="131185980000000000" Dst="0" />
<file name="spinning.less" server="9fcd069a.7host.cn:90" local="131237379376261957" remote="131185980000000000" Dst="0" />
<file name="variables.less" server="9fcd069a.7host.cn:90" local="131237379379074493" remote="131185980000000000" Dst="0" />
<file name="stacked.less" server="9fcd069a.7host.cn:90" local="131237379380012003" remote="131185980000000000" Dst="0" />
</dwsync>